scalarstop/__init__.py
scalarstop/_attr_dict.py
scalarstop/_constants.py
scalarstop/_cpu.py
scalarstop/_datetime.py
scalarstop/_filesystem.py
scalarstop/_keras_callbacks.py
scalarstop/_logging.py
scalarstop/_naming.py
scalarstop/_single_namespace.py
scalarstop/_tfdata.py
scalarstop/datablob.py
scalarstop/datablob_metadata.py
scalarstop/dataclasses.py
scalarstop/exceptions.py
scalarstop/hyperparams.py
scalarstop/model.py
scalarstop/model_template.py
scalarstop/pickle.py
scalarstop/tf_config.py
scalarstop/train_store.py
scalarstop/warnings.py
scalarstop-6.0.0.dist-info/LICENSE
scalarstop-6.0.0.dist-info/WHEEL
scalarstop-6.0.0.dist-info/METADATA
scalarstop-6.0.0.dist-info/RECORD
