Metadata-Version: 2.1
Name: scalarstop
Version: 6.0.0
Summary: A framework for managing machine learning experiments.
Home-page: https://www.scalarstop.com
License: MIT
Author: Neocrym Records Inc
Author-email: engineering@neocrym.com
Requires-Python: >=3.8,<3.11
Classifier: License :: OSI Approved :: MIT License
Classifier: Programming Language :: Python :: 3
Classifier: Programming Language :: Python :: 3.10
Classifier: Programming Language :: Python :: 3.8
Classifier: Programming Language :: Python :: 3.9
Provides-Extra: psycopg2
Provides-Extra: psycopg2-binary
Provides-Extra: tensorflow
Provides-Extra: tensorflow-gpu
Requires-Dist: SQLAlchemy (>=1.4,<2.0)
Requires-Dist: alembic (>=1.7,<2.0)
Requires-Dist: cloudpickle (>=2.0,<3.0)
Requires-Dist: log-with-context
Requires-Dist: numpy (>=1.20); python_version < "3.10"
Requires-Dist: numpy (>=1.22); python_version >= "3.10" and python_version < "3.11"
Requires-Dist: pandas
Requires-Dist: psycopg2 (>=2.9.3,<3.0.0); extra == "psycopg2"
Requires-Dist: psycopg2-binary (>=2.9.3,<3.0.0); extra == "psycopg2-binary"
Requires-Dist: tensorflow (>=2.8); extra == "tensorflow"
Requires-Dist: tensorflow-gpu (>=2.8); extra == "tensorflow-gpu"
Project-URL: Repository, https://github.com/scalarstop/scalarstop
